bored_api/__init__.py
bored_api/bored_api.py
bored_api/py.typed
bored_api-1.1.1.dist-info/LICENSE
bored_api-1.1.1.dist-info/METADATA
bored_api-1.1.1.dist-info/WHEEL
bored_api-1.1.1.dist-info/top_level.txt
bored_api-1.1.1.dist-info/RECORD
